TrafficLight/TrafficLightFSM.v
module TrafficLightFSM (
    input clk,                              // Clock signal
    input reset,                            // Reset signal
    output reg [2:0] light                  // 3-bit output for traffic light (RED, YELLOW, GREEN)
);

    // State encoding
    parameter RED = 3'b100;
    parameter GREEN = 3'b001;
    parameter YELLOW = 3'b010;

    // Registers
    reg [2:0] current_state, next_state;

    // State transition block
    always @(posedge clk or posedge reset) begin
        if (reset)
            current_state <= RED;
        else
            current_state <= next_state;
    end

    // Next state logic
    always @(*) begin
        case (current_state)
            RED: begin
                next_state = GREEN; // Transition from RED => GREEN
            end
            GREEN: begin
                next_state = YELLOW; // Transition from GREEN => YELLOW
            end
            YELLOW: begin
                next_state = RED; // Transition from YELLOW => RED
            end
            default: begin
                next_state = RED; // Default state => RED
            end
        endcase
    end

     // Output logic
    always @(*) begin
        case (current_state)
            RED: light = RED;
            GREEN: light = GREEN;
            YELLOW: light = YELLOW;
            default: light = RED;
        endcase
    end

endmodule

TrafficLight/TrafficLightFSM_tb.v
module TrafficLightFSM_tb;

    // Testbench signals
    reg clk;
    reg reset;
    wire [2:0] light;

    // Instantiate the TrafficLightFSM module
    TrafficLightFSM uut (
        .clk(clk),
        .reset(reset),
        .light(light)
    );

    // Clock generation
    initial begin
        clk = 0;
        forever #5 clk = ~clk; // Toggle clock every 5 ns
    end

     // Test sequence
    initial begin
        // simulation dump file 
        $dumpfile("TrafficLightFSM_tb.vcd");
        $dumpvars(0, TrafficLightFSM_tb);

        // Apply reset
        $display("Starting simulation...");
        reset = 1;
        #10;
        reset = 0;

        // Light transitions
        $display("Time(ns) | Reset | Light State");
        $monitor("%0dns | %b     | %b", $time, reset, light);

        // Run for a few clock cycles
        #100;

        // Test with reset during operation
        $display("Applying reset during operation...");
        reset = 1;
        #10;
        reset = 0;

        // Run for a few clock cycles
        #100;

        // End simulation
        $display("Ending simulation.");
        $finish;
    end
endmodule

TrafficLight/TrafficLightFSM_tb.vcd
$date
	Tue Dec 24 20:16:23 2024
$end
$version
	Icarus Verilog
$end
$timescale
	1s
$end
$scope module TrafficLightFSM_tb $end
$var wire 3 ! light [2:0] $end
$var reg 1 " clk $end
$var reg 1 # reset $end
$scope module uut $end
$var wire 1 " clk $end
$var wire 1 # reset $end
$var parameter 3 $ GREEN $end
$var parameter 3 % RED $end
$var parameter 3 & YELLOW $end
$var reg 3 ' current_state [2:0] $end
$var reg 3 ( light [2:0] $end
$var reg 3 ) next_state [2:0] $end
$upscope $end
$upscope $end
$enddefinitions $end
$comment Show the parameter values. $end
$dumpall
b10 &
b100 %
b1 $
$end
#0
$dumpvars
b1 )
b100 (
b100 '
1#
0"
b100 !
$end
#5
1"
#10
0"
0#
#15
b10 )
b1 !
b1 (
b1 '
1"
#20
0"
#25
b10 !
b10 (
b100 )
b10 '
1"
#30
0"
#35
b1 )
b100 !
b100 (
b100 '
1"
#40
0"
#45
b1 !
b1 (
b10 )
b1 '
1"
#50
0"
#55
b100 )
b10 !
b10 (
b10 '
1"
#60
0"
#65
b100 !
b100 (
b1 )
b100 '
1"
#70
0"
#75
b10 )
b1 !
b1 (
b1 '
1"
#80
0"
#85
b10 !
b10 (
b100 )
b10 '
1"
#90
0"
#95
b1 )
b100 !
b100 (
b100 '
1"
#100
0"
#105
b1 !
b1 (
b10 )
b1 '
1"
#110
b1 )
b100 !
b100 (
b100 '
0"
1#
#115
1"
#120
0"
0#
#125
b1 !
b1 (
b10 )
b1 '
1"
#130
0"
#135
b100 )
b10 !
b10 (
b10 '
1"
#140
0"
#145
b100 !
b100 (
b1 )
b100 '
1"
#150
0"
#155
b10 )
b1 !
b1 (
b1 '
1"
#160
0"
#165
b10 !
b10 (
b100 )
b10 '
1"
#170
0"
#175
b1 )
b100 !
b100 (
b100 '
1"
#180
0"
#185
b1 !
b1 (
b10 )
b1 '
1"
#190
0"
#195
b100 )
b10 !
b10 (
b10 '
1"
#200
0"
#205
b100 !
b100 (
b1 )
b100 '
1"
#210
0"
#215
b10 )
b1 !
b1 (
b1 '
1"
