TrafficLight/TrafficLightFSM.v
`timescale 1ns / 1ps

//////////////////////////////////////////////////////////////////////////////////
// Author: Nima Bargestan
// 
// Create Date: 12/24/2024
// Design Name: Traffic Light FSM in Verilog
// Module Name: TrafficLightFSM
// Description: 
//      This module implements a Traffic Light FSM. It generates sequential light transitions 
//      (RED, YELLOW, GREEN) based on a configurable timer. Each state duration is controlled 
//      by the clock cycles defined for each light state. The FSM transitions states based on 
//      the timer and reset conditions.
// 
// Usage:
//     - Use this testbench to validate the TrafficLightFSM module.
//     - Observe output waveforms or console logs for debugging and verification.
//
// Dependencies: None
//
//////////////////////////////////////////////////////////////////////////////////

module TrafficLightFSM (
    input clk,                              // Clock signal
    input reset,                            // Reset signal
    output reg [2:0] light                  // 3-bit output for traffic light (RED, YELLOW, GREEN)
);

    // State encoding
    parameter RED = 3'b100;
    parameter GREEN = 3'b001;
    parameter YELLOW = 3'b010;

    // State duration parameters (in CC)
    parameter RED_TIME = 10;
    parameter GREEN_TIME = 10;
    parameter YELLOW_TIME = 5;

    // Registers (+ timer)
    reg [2:0] current_state, next_state;
    reg [3:0] timer;                         // Timer to count clock cycles for each state

    // State transition block + timer
    always @(posedge clk or posedge reset) begin
        if (reset) begin
            current_state <= RED;
            timer <= 0;
        end else if (timer == 0) begin
            current_state <= next_state;
            case (next_state)
                RED: timer <= RED_TIME;
                GREEN: timer <= GREEN_TIME;
                YELLOW: timer <= YELLOW_TIME;
            endcase
        end else begin
            timer <= timer - 1;
        end
    end

    // Next state logic
    always @(*) begin
        case (current_state)
            RED: begin
                next_state = GREEN; // Transition from RED => GREEN
            end
            GREEN: begin
                next_state = YELLOW; // Transition from GREEN => YELLOW
            end
            YELLOW: begin
                next_state = RED; // Transition from YELLOW => RED
            end
            default: begin
                next_state = RED; // Default state => RED
            end
        endcase
    end

     // Output logic
    always @(*) begin
        case (current_state)
            RED: light = RED;
            GREEN: light = GREEN;
            YELLOW: light = YELLOW;
            default: light = RED;
        endcase
    end

endmodule

TrafficLight/TrafficLightFSM_tb.v
module TrafficLightFSM_tb;

    // Testbench signals
    reg clk;
    reg reset;
    wire [2:0] light;

    // Instantiate the TrafficLightFSM module
    TrafficLightFSM uut (
        .clk(clk),
        .reset(reset),
        .light(light)
    );

    // Clock generator
    initial begin
        clk = 0;
        forever #5 clk = ~clk; 
    end

    // Test sequence
    initial begin
        // simulation dump file 
        $dumpfile("TrafficLightFSM_tb.vcd");
        $dumpvars(0, TrafficLightFSM_tb);

        // Apply reset
        $display("Starting simulation...");
        reset = 1;
        #10;
        reset = 0;

        // Light transitions
        $display("Time(ns) | Reset | Light State");
        $monitor("%0dns | %b     | %b", $time, reset, light);

        // Run for a few clock cycles
        #1000;

        // Test with reset during operation
        $display("Applying reset during operation...");
        reset = 1;
        #10;
        reset = 0;

        // Run for a few clock cycles
        #1000;

        // End simulation
        $display("Ending simulation.");
        $finish;
    end

     // Debugging aid
    initial begin
        forever begin
            #5;
            if (light == 3'b100) $display("Time: %0dns - RED State", $time);
            else if (light == 3'b001) $display("Time: %0dns - GREEN State", $time);
            else if (light == 3'b010) $display("Time: %0dns - YELLOW State", $time);
        end
    end

endmodule

TrafficLight/TrafficLightFSM_tb.vcd
$date
	Tue Dec 24 21:00:13 2024
$end
$version
	Icarus Verilog
$end
$timescale
	1s
$end
$scope module TrafficLightFSM_tb $end
$var wire 3 ! light [2:0] $end
$var reg 1 " clk $end
$var reg 1 # reset $end
$scope module uut $end
$var wire 1 " clk $end
$var wire 1 # reset $end
$var parameter 3 $ GREEN $end
$var parameter 32 % GREEN_TIME $end
$var parameter 3 & RED $end
$var parameter 32 ' RED_TIME $end
$var parameter 3 ( YELLOW $end
$var parameter 32 ) YELLOW_TIME $end
$var reg 3 * current_state [2:0] $end
$var reg 3 + light [2:0] $end
$var reg 3 , next_state [2:0] $end
$var reg 4 - timer [3:0] $end
$upscope $end
$upscope $end
$enddefinitions $end
$comment Show the parameter values. $end
$dumpall
b101 )
b10 (
b1010 '
b100 &
b1010 %
b1 $
$end
#0
$dumpvars
b0 -
b1 ,
b100 +
b100 *
1#
0"
b100 !
$end
#5
1"
#10
0"
0#
#15
b10 ,
b1 !
b1 +
b1010 -
b1 *
1"
#20
0"
#25
b1001 -
1"
#30
0"
#35
b1000 -
1"
#40
0"
#45
b111 -
1"
#50
0"
#55
b110 -
1"
#60
0"
#65
b101 -
1"
#70
0"
#75
b100 -
1"
#80
0"
#85
b11 -
1"
#90
0"
#95
b10 -
1"
#100
0"
#105
b1 -
1"
#110
0"
#115
b0 -
1"
#120
0"
#125
b10 !
b10 +
b100 ,
b101 -
b10 *
1"
#130
0"
#135
b100 -
1"
#140
0"
#145
b11 -
1"
#150
0"
#155
b10 -
1"
#160
0"
#165
b1 -
1"
#170
0"
#175
b0 -
1"
#180
0"
#185
b1 ,
b100 !
b100 +
b1010 -
b100 *
1"
#190
0"
#195
b1001 -
1"
#200
0"
#205
b1000 -
1"
#210
0"
#215
b111 -
1"
#220
0"
#225
b110 -
1"
#230
0"
#235
b101 -
1"
#240
0"
#245
b100 -
1"
#250
0"
#255
b11 -
1"
#260
0"
#265
b10 -
1"
#270
0"
#275
b1 -
1"
#280
0"
#285
b0 -
1"
#290
0"
#295
b1 !
b1 +
b10 ,
b1010 -
b1 *
1"
#300
0"
#305
b1001 -
1"
#310
0"
#315
b1000 -
1"
#320
0"
#325
b111 -
1"
#330
0"
#335
b110 -
1"
#340
0"
#345
b101 -
1"
#350
0"
#355
b100 -
1"
#360
0"
#365
b11 -
1"
#370
0"
#375
b10 -
1"
#380
0"
#385
b1 -
1"
#390
0"
#395
b0 -
1"
#400
0"
#405
b100 ,
b10 !
b10 +
b101 -
b10 *
1"
#410
0"
#415
b100 -
1"
#420
0"
#425
b11 -
1"
#430
0"
#435
b10 -
1"
#440
0"
#445
b1 -
1"
#450
0"
#455
b0 -
1"
#460
0"
#465
b100 !
b100 +
b1 ,
b1010 -
b100 *
1"
#470
0"
#475
b1001 -
1"
#480
0"
#485
b1000 -
1"
#490
0"
#495
b111 -
1"
#500
0"
#505
b110 -
1"
#510
0"
#515
b101 -
1"
#520
0"
#525
b100 -
1"
#530
0"
#535
b11 -
1"
#540
0"
#545
b10 -
1"
#550
0"
#555
b1 -
1"
#560
0"
#565
b0 -
1"
#570
0"
#575
b10 ,
b1 !
b1 +
b1010 -
b1 *
1"
#580
0"
#585
b1001 -
1"
#590
0"
#595
b1000 -
1"
#600
0"
#605
b111 -
1"
#610
0"
#615
b110 -
1"
#620
0"
#625
b101 -
1"
#630
0"
#635
b100 -
1"
#640
0"
#645
b11 -
1"
#650
0"
#655
b10 -
1"
#660
0"
#665
b1 -
1"
#670
0"
#675
b0 -
1"
#680
0"
#685
b10 !
b10 +
b100 ,
b101 -
b10 *
1"
#690
0"
#695
b100 -
1"
#700
0"
#705
b11 -
1"
#710
0"
#715
b10 -
1"
#720
0"
#725
b1 -
1"
#730
0"
#735
b0 -
1"
#740
0"
#745
b1 ,
b100 !
b100 +
b1010 -
b100 *
1"
#750
0"
#755
b1001 -
1"
#760
0"
#765
b1000 -
1"
#770
0"
#775
b111 -
1"
#780
0"
#785
b110 -
1"
#790
0"
#795
b101 -
1"
#800
0"
#805
b100 -
1"
#810
0"
#815
b11 -
1"
#820
0"
#825
b10 -
1"
#830
0"
#835
b1 -
1"
#840
0"
#845
b0 -
1"
#850
0"
#855
b1 !
b1 +
b10 ,
b1010 -
b1 *
1"
#860
0"
#865
b1001 -
1"
#870
0"
#875
b1000 -
1"
#880
0"
#885
b111 -
1"
#890
0"
#895
b110 -
1"
#900
0"
#905
b101 -
1"
#910
0"
#915
b100 -
1"
#920
0"
#925
b11 -
1"
#930
0"
#935
b10 -
1"
#940
0"
#945
b1 -
1"
#950
0"
#955
b0 -
1"
#960
0"
#965
b100 ,
b10 !
b10 +
b101 -
b10 *
1"
#970
0"
#975
b100 -
1"
#980
0"
#985
b11 -
1"
#990
0"
#995
b10 -
1"
#1000
0"
#1005
b1 -
1"
#1010
b100 !
b100 +
b1 ,
b0 -
b100 *
0"
1#
#1015
1"
#1020
0"
0#
#1025
b10 ,
b1 !
b1 +
b1010 -
b1 *
1"
#1030
0"
#1035
b1001 -
1"
#1040
0"
#1045
b1000 -
1"
#1050
0"
#1055
b111 -
1"
#1060
0"
#1065
b110 -
1"
#1070
0"
#1075
b101 -
1"
#1080
0"
#1085
b100 -
1"
#1090
0"
#1095
b11 -
1"
#1100
0"
#1105
b10 -
1"
#1110
0"
#1115
b1 -
1"
#1120
0"
#1125
b0 -
1"
#1130
0"
#1135
b10 !
b10 +
b100 ,
b101 -
b10 *
1"
#1140
0"
#1145
b100 -
1"
#1150
0"
#1155
b11 -
1"
#1160
0"
#1165
b10 -
1"
#1170
0"
#1175
b1 -
1"
#1180
0"
#1185
b0 -
1"
#1190
0"
#1195
b1 ,
b100 !
b100 +
b1010 -
b100 *
1"
#1200
0"
#1205
b1001 -
1"
#1210
0"
#1215
b1000 -
1"
#1220
0"
#1225
b111 -
1"
#1230
0"
#1235
b110 -
1"
#1240
0"
#1245
b101 -
1"
#1250
0"
#1255
b100 -
1"
#1260
0"
#1265
b11 -
1"
#1270
0"
#1275
b10 -
1"
#1280
0"
#1285
b1 -
1"
#1290
0"
#1295
b0 -
1"
#1300
0"
#1305
b1 !
b1 +
b10 ,
b1010 -
b1 *
1"
#1310
0"
#1315
b1001 -
1"
#1320
0"
#1325
b1000 -
1"
#1330
0"
#1335
b111 -
1"
#1340
0"
#1345
b110 -
1"
#1350
0"
#1355
b101 -
1"
#1360
0"
#1365
b100 -
1"
#1370
0"
#1375
b11 -
1"
#1380
0"
#1385
b10 -
1"
#1390
0"
#1395
b1 -
1"
#1400
0"
#1405
b0 -
1"
#1410
0"
#1415
b100 ,
b10 !
b10 +
b101 -
b10 *
1"
#1420
0"
#1425
b100 -
1"
#1430
0"
#1435
b11 -
1"
#1440
0"
#1445
b10 -
1"
#1450
0"
#1455
b1 -
1"
#1460
0"
#1465
b0 -
1"
#1470
0"
#1475
b100 !
b100 +
b1 ,
b1010 -
b100 *
1"
#1480
0"
#1485
b1001 -
1"
#1490
0"
#1495
b1000 -
1"
#1500
0"
#1505
b111 -
1"
#1510
0"
#1515
b110 -
1"
#1520
0"
#1525
b101 -
1"
#1530
0"
#1535
b100 -
1"
#1540
0"
#1545
b11 -
1"
#1550
0"
#1555
b10 -
1"
#1560
0"
#1565
b1 -
1"
#1570
0"
#1575
b0 -
1"
#1580
0"
#1585
b10 ,
b1 !
b1 +
b1010 -
b1 *
1"
#1590
0"
#1595
b1001 -
1"
#1600
0"
#1605
b1000 -
1"
#1610
0"
#1615
b111 -
1"
#1620
0"
#1625
b110 -
1"
#1630
0"
#1635
b101 -
1"
#1640
0"
#1645
b100 -
1"
#1650
0"
#1655
b11 -
1"
#1660
0"
#1665
b10 -
1"
#1670
0"
#1675
b1 -
1"
#1680
0"
#1685
b0 -
1"
#1690
0"
#1695
b10 !
b10 +
b100 ,
b101 -
b10 *
1"
#1700
0"
#1705
b100 -
1"
#1710
0"
#1715
b11 -
1"
#1720
0"
#1725
b10 -
1"
#1730
0"
#1735
b1 -
1"
#1740
0"
#1745
b0 -
1"
#1750
0"
#1755
b1 ,
b100 !
b100 +
b1010 -
b100 *
1"
#1760
0"
#1765
b1001 -
1"
#1770
0"
#1775
b1000 -
1"
#1780
0"
#1785
b111 -
1"
#1790
0"
#1795
b110 -
1"
#1800
0"
#1805
b101 -
1"
#1810
0"
#1815
b100 -
1"
#1820
0"
#1825
b11 -
1"
#1830
0"
#1835
b10 -
1"
#1840
0"
#1845
b1 -
1"
#1850
0"
#1855
b0 -
1"
#1860
0"
#1865
b1 !
b1 +
b10 ,
b1010 -
b1 *
1"
#1870
0"
#1875
b1001 -
1"
#1880
0"
#1885
b1000 -
1"
#1890
0"
#1895
b111 -
1"
#1900
0"
#1905
b110 -
1"
#1910
0"
#1915
b101 -
1"
#1920
0"
#1925
b100 -
1"
#1930
0"
#1935
b11 -
1"
#1940
0"
#1945
b10 -
1"
#1950
0"
#1955
b1 -
1"
#1960
0"
#1965
b0 -
1"
#1970
0"
#1975
b100 ,
b10 !
b10 +
b101 -
b10 *
1"
#1980
0"
#1985
b100 -
1"
#1990
0"
#1995
b11 -
1"
#2000
0"
#2005
b10 -
1"
#2010
0"
#2015
b1 -
1"
